lbmblood/__init__.py
lbmblood/lbmblood.py
lbmblood-0.0.1.dist-info/LICENSE
lbmblood-0.0.1.dist-info/METADATA
lbmblood-0.0.1.dist-info/WHEEL
lbmblood-0.0.1.dist-info/top_level.txt
lbmblood-0.0.1.dist-info/RECORD
