Metadata-Version: 2.1
Name: lbmblood
Version: 0.0.1
Summary: lbmblood simulation
Home-page: https://github.com/wistbean/learn_python3_spider
Author: lokigadfly
Author-email: lokigadfly@gmail.com
License: UNKNOWN
Platform: UNKNOWN
